lightmlrestapi/__init__.py
lightmlrestapi/__main__.py
lightmlrestapi/args/__init__.py
lightmlrestapi/args/args_images.py
lightmlrestapi/args/encrypt_helper.py
lightmlrestapi/args/zip_helper.py
lightmlrestapi/cli/__init__.py
lightmlrestapi/cli/make_encrypt_pwd.py
lightmlrestapi/cli/make_ml_app.py
lightmlrestapi/cli/make_ml_store.py
lightmlrestapi/cli/make_ml_upload.py
lightmlrestapi/mlapp/__init__.py
lightmlrestapi/mlapp/authfiction.py
lightmlrestapi/mlapp/base_logging.py
lightmlrestapi/mlapp/mlpost_rest.py
lightmlrestapi/mlapp/mlstorage.py
lightmlrestapi/mlapp/mlstorage_rest.py
lightmlrestapi/netrest/__init__.py
lightmlrestapi/netrest/rest_helper.py
lightmlrestapi/testing/__init__.py
lightmlrestapi/testing/dummy_applications.py
lightmlrestapi/testing/template_dl_keras.py
lightmlrestapi/testing/template_dl_light.py
lightmlrestapi/testing/template_dl_torch.py
lightmlrestapi/testing/template_ml.py
lightmlrestapi/testing/data/__init__.py
lightmlrestapi/testing/data/wiki.png
lightmlrestapi/tools/__init__.py
lightmlrestapi/tools/json_helper.py
lightmlrestapi-0.3.192.dist-info/LICENSE.txt
lightmlrestapi-0.3.192.dist-info/METADATA
lightmlrestapi-0.3.192.dist-info/WHEEL
lightmlrestapi-0.3.192.dist-info/top_level.txt
lightmlrestapi-0.3.192.dist-info/RECORD
