Metadata-Version: 2.1
Name: lightmlrestapi
Version: 0.3.192
Summary: Light REST API for machine learned models
Home-page: http://www.xavierdupre.fr/app/lightmlrestapi/helpsphinx/index.html
Author: Xavier Dupré
Author-email: xavier.dupre@gmail.com
License: MIT
Download-URL: https://github.com/sdpython/lightmlrestapi/
Keywords: lightmlrestapi,Xavier Dupré
Platform: UNKNOWN
Classifier: Programming Language :: Python :: 3
Classifier: Intended Audience :: Developers
Classifier: Topic :: Scientific/Engineering
Classifier: Topic :: Education
Classifier: License :: OSI Approved :: MIT License
Classifier: Development Status :: 5 - Production/Stable
Requires-Dist: ujson
Requires-Dist: falcon (>=2.0)
Requires-Dist: msgpack-numpy
Requires-Dist: waitress
Requires-Dist: PyJWT
Requires-Dist: requests
Provides-Extra: cli
Requires-Dist: pyquickhelper ; extra == 'cli'
